setup.py
nuances/main.py
nuances-0.0.1.dist-info/METADATA
nuances-0.0.1.dist-info/WHEEL
nuances-0.0.1.dist-info/licenses/LICENSE
nuances-0.0.1.dist-info/RECORD
