Metadata-Version: 2.1
Name: nuances
Version: 0.0.1
Summary: ...
Project-URL: Homepage, https://github.com/bglbrt/NUANCES
Project-URL: Bug Tracker, https://github.com/bglbrt/NUANCES/issues
Author: bglbrt
License-File: LICENSE
Classifier: License :: OSI Approved :: MIT License
Classifier: Operating System :: OS Independent
Classifier: Programming Language :: Python :: 3
Requires-Python: >=3.7
